halopy/__init__.py
halopy-1.1.dist-info/top_level.txt
halopy-1.1.dist-info/METADATA
halopy-1.1.dist-info/DESCRIPTION.rst
halopy-1.1.dist-info/metadata.json
halopy-1.1.dist-info/WHEEL
halopy-1.1.dist-info/RECORD
