Metadata-Version: 2.0
Name: halopy
Version: 1.1
Summary: Halo 5 API wrapper for python
Home-page: https://github.com/maxpowa/halopy
Author: Max Gurela
Author-email: maxpowa@outlook.com
License: Eiffel Forum License 2
Platform: UNKNOWN
Requires-Dist: requests
Requires-Dist: requests-cache
